ycd/__init__.py
ycd/__main__.py
ycd/arguments.py
ycd/config.py
ycd/downloader.py
ycd/exceptions.py
ycd/logger.py
ycd/mylogger.py
ycd/myutil.py
ycd/progressbar.py
ycd/settings.py
ycd/settings.reference.json.py
ycd/settings2.py
ycd/singleton.py
ycd/videoinfo2.py
ycd/youtube/__init__.py
ycd/youtube/api.py
ycd/youtube/channel.py
ycd/youtube/local_playlist.py
ycd/youtube/playlist.py
ycd/youtube/proto.py
ycd/youtube/subscriptions.py
ycd/youtube/util.py
ycd/youtube/yt_data_extract/__init__.py
ycd/youtube/yt_data_extract/common.py
ycd/youtube/yt_data_extract/everything_else.py
ycd/youtube/yt_data_extract/watch_extraction.py
ycd-0.9.7.dist-info/LICENSE
ycd-0.9.7.dist-info/METADATA
ycd-0.9.7.dist-info/WHEEL
ycd-0.9.7.dist-info/entry_points.txt
ycd-0.9.7.dist-info/top_level.txt
ycd-0.9.7.dist-info/RECORD
