Metadata-Version: 2.1
Name: ycd
Version: 0.9.7
Home-page: http://example.com
Author: vb
Author-email: i@s.biz
License: AGPLv3
Classifier: Natural Language :: English
Classifier: Development Status :: 4 - Beta
Classifier: Programming Language :: Python
Classifier: Programming Language :: Python :: 3.7
Classifier: Programming Language :: Python :: 3.8
Classifier: Programming Language :: Python :: 3.9
Classifier: Programming Language :: Python :: 3.10
Classifier: Programming Language :: Python :: 3.11
Classifier: License :: OSI Approved :: GNU Affero General Public License v3
License-File: LICENSE
Requires-Dist: chat-downloader
Requires-Dist: requests
Requires-Dist: emoji
Requires-Dist: Flask >=1.0.3
Requires-Dist: gevent >=1.2.2
Requires-Dist: Brotli >=1.0.7
Requires-Dist: PySocks >=1.6.8
Requires-Dist: urllib3 >=1.24.1
Requires-Dist: defusedxml >=0.5.0
Requires-Dist: cachetools >=4.0.0
Requires-Dist: stem >=1.8.0
